theory_game/__init__.py
theory_game/theory_game.py
theory_game-1.9.1.dist-info/LICENSE
theory_game-1.9.1.dist-info/METADATA
theory_game-1.9.1.dist-info/WHEEL
theory_game-1.9.1.dist-info/top_level.txt
theory_game-1.9.1.dist-info/RECORD
