Metadata-Version: 2.1
Name: theory-game
Version: 1.9.1
Summary: A package for EGE 19-21 tasks in computer science dedicated to game theory
Home-page: https://pypi.org/
Author: Denis Perkov
Author-email: denisperkov0@gmail.com
License: UNKNOWN
Platform: UNKNOWN
Classifier: Programming Language :: Python :: 3.10
Classifier: License :: OSI Approved :: MIT License
Classifier: Operating System :: OS Independent
Requires-Python: >=3.6
License-File: LICENSE
